Metadata-Version: 1.1
Name: ciag-robot
Version: 0.0.1
Summary: Python Library to Build Web Robots
Home-page: https://github.com/OpenCIAg/py-robot
Author: Éttore Leandro Tognoli
Author-email: ettore.tognoli@ciag.org.br
License: CLOSED
Download-URL: https://github.com/OpenCIAg/py-robot/tree/0.0.1/
Keywords: Robot,Web Crawler
Platform: UNKNOWN
Classifier: Operating System :: OS Independent
Classifier: Programming Language :: Python :: 3
Classifier: Development Status :: 3 - Alpha
